[
  {
    "url": "https://ruvds.com/ru/vps_start",
    "name": "Дешёвые VPS с тарифом Старт - всего 139 рублей в месяц",
    "snippet": "VPS СЕРВЕРЫ от 139 ₽ в месяц Тарифы без ограничений* * В тарифе за 139 руб действуют ограничения условиях. Дата-центры расположены в ряде городов России и стра ...",
    "host_name": "ruvds.com",
    "rank": 0,
    "date": "",
    "favicon": ""
  },
  {
    "url": "https://easylinklife.com/providers/ruvds",
    "name": "RUVDS 2026: 20 DC, ISO 27001, VPS от 139₽, промо - EasyLinkLife",
    "snippet": "RUVDS предоставляет: 3 дня теста на тарифах до 3000₽ (до 4 vCPU, 10 ГБ RAM, 300 ГБ диск, 2 IPv4, лимит 50 ГБ трафика/сутки), бесплатный ...",
    "host_name": "easylinklife.com",
    "rank": 1,
    "date": "",
    "favicon": ""
  },
  {
    "url": "https://hosters.ru/ruvds",
    "name": "RuVDS (ruvds.com): честный обзор и тарифы 2026 - HOSTERS",
    "snippet": "Старт. 1 2.00 ГГц, 0.5 Гб. Hyper-V. 10 Гб, 139 ₽ / меc. %. Старт SSD. 1 2.20 ГГц. Hyper-V. 10 Гб. SSD. 209 ₽ / меc. %. Старт Hit. 1 Гб. Hyper-V. 20 Гб, 259 ₽ / ...",
    "host_name": "hosters.ru",
    "rank": 2,
    "date": "",
    "favicon": ""
  },
  {
    "url": "https://hostinghub.ru/ruvds",
    "name": "Обзор хостинга RuVDS (РуВДС) - HostingHUB",
    "snippet": "Количество IPv4: от 1 до 16 шт. стоит 3156 рублей в месяц. START (Hyper-V) 139 руб. 1334 руб. START SSD (Hyper-V) Россия 0.50 Гб. Скрытые ограничения.",
    "host_name": "hostinghub.ru",
    "rank": 3,
    "date": "",
    "favicon": ""
  },
  {
    "url": "https://www.whtop.com/plans/ruvds.com/119321",
    "name": "Start Hit > ruvds.com, RUB 259.00/mo. on VPS, Linux - WHTop",
    "snippet": "Старт Хит is a stepped-up Linux VPS at 259 RUB/month, keeping the same 1 vCPU and 1 dedicated IPv4 while increasing memory and disk. The ...",
    "host_name": "www.whtop.com",
    "rank": 4,
    "date": "",
    "favicon": ""
  },
  {
    "url": "https://ruvds.com/ru/faq/start",
    "name": "Тариф Старт Archives - Справочник RuVDS",
    "snippet": "Старт От 139 рублей/мес Ref прописывать РTR-записи IP-адресам, данных тарифных планов? Нет, трафик безлимитный.",
    "host_name": "ruvds.com",
    "rank": 5,
    "date": "",
    "favicon": ""
  },
  {
    "url": "https://habr.com/ru/companies/ruvds/articles/464571/comments",
    "name": "Мозг + VPS за 30 рублей =? / Комментарии / Хабр",
    "snippet": "аренда IPv4 адресов. VPS за 30 рублей. Старт от 130 рублей в месяц без ограничений с бесплатной тарифах действует бесплатная круглосуточная тех ...",
    "host_name": "habr.com",
    "rank": 6,
    "date": "",
    "favicon": ""
  },
  {
    "url": "https://market.cnews.ru/tariff/118936",
    "name": "Тариф Старт Hit компании RuVDS по услуге VPSVDS",
    "snippet": "Состав тарифа Ядер CPU: 1 x 2.2 ГГц RAM: 1 Гб HDD: 20 Гб ОС: Linux Тип HDD: SATA 240 руб. Старт 139 руб. 25% Маркет Market.CNews:",
    "host_name": "market.cnews.ru",
    "rank": 7,
    "date": "",
    "favicon": ""
  },
  {
    "url": "https://ru.hostings.info/ruvds-com.html",
    "name": "RuVDS Отзывы, Обзор, Акции, Тарифы - Hostings.info",
    "snippet": "Оплатил VPS по тарифу “Старт”, деньги списали, сервер не запустился. Поддержка ответила уже после оплаты, что тариф “временно недоступен из-за нехватки ресурсов ...",
    "host_name": "ru.hostings.info",
    "rank": 8,
    "date": "",
    "favicon": ""
  },
  {
    "url": "https://eto-razvod.ru/review/ruvds",
    "name": "RUVDS - Хостинг провайдеры - Это развод",
    "snippet": "Облачный провайдер RUVDS предлагает услугу аренды ПО с 2016 года. Это дает клиентам возможность отказаться от покупки и хранения физических ...",
    "host_name": "eto-razvod.ru",
    "rank": 9,
    "date": "",
    "favicon": ""
  }
]